sinapsis_rfdetr/__init__.py
sinapsis_rfdetr/helpers/__init__.py
sinapsis_rfdetr/helpers/rfdetr_helpers.py
sinapsis_rfdetr/helpers/tags.py
sinapsis_rfdetr/templates/__init__.py
sinapsis_rfdetr/templates/rfdetr_export.py
sinapsis_rfdetr/templates/rfdetr_inference.py
sinapsis_rfdetr/templates/rfdetr_model_base.py
sinapsis_rfdetr/templates/rfdetr_train.py
sinapsis_rfdetr-0.1.13.dist-info/licenses/LICENSE
sinapsis_rfdetr-0.1.13.dist-info/METADATA
sinapsis_rfdetr-0.1.13.dist-info/WHEEL
sinapsis_rfdetr-0.1.13.dist-info/top_level.txt
sinapsis_rfdetr-0.1.13.dist-info/RECORD
