Metadata-Version: 2.4
Name: sinapsis-rfdetr
Version: 0.1.13
Summary: Training and inference templates based on the RF-DETR object detection model
Author-email: SinapsisAI <dev@sinapsis.tech>
Project-URL: Homepage, https://sinapsis.tech
Project-URL: Documentation, https://docs.sinapsis.tech/docs
Project-URL: Tutorials, https://docs.sinapsis.tech/tutorials
Project-URL: Repository, https://github.com/Sinapsis-AI/sinapsis-object-detection.git
Requires-Python: >=3.10
License-File: LICENSE
Requires-Dist: numpy==1.26.4
Requires-Dist: onnxruntime>=1.21.0
Requires-Dist: protobuf==3.20.2
Requires-Dist: rfdetr[metrics]==1.2.1
Requires-Dist: sinapsis>=0.1.1
Provides-Extra: all
Requires-Dist: sinapsis-rfdetr[data-tools]; extra == "all"
Provides-Extra: data-tools
Requires-Dist: sinapsis-data-readers>=0.1.2; extra == "data-tools"
Requires-Dist: sinapsis-data-visualization[all]>=0.1.0; extra == "data-tools"
Requires-Dist: sinapsis-data-writers[all]>=0.1.1; extra == "data-tools"
Dynamic: license-file
